setup.cfg
setup.py
nose_hipchat.egg-info/PKG-INFO
nose_hipchat.egg-info/SOURCES.txt
nose_hipchat.egg-info/dependency_links.txt
nose_hipchat.egg-info/entry_points.txt
nose_hipchat.egg-info/requires.txt
nose_hipchat.egg-info/top_level.txt
nosehipchat/__init__.py
nosehipchat/nosehipchat.py
nosehipchat/version.py