Metadata-Version: 1.1
Name: nose-hipchat
Version: 0.0.1
Summary: Nose plugin to post test results to HipChat
Home-page: https://github.com/sleibman/nose-hipchat
Author: Steve Leibman
Author-email: sleibman@alum.mit.edu
License: MIT License
Platform: UNKNOWN
Classifier: Topic :: Software Development :: Testing
Classifier: Intended Audience :: Developers
Classifier: License :: OSI Approved :: MIT License
Classifier: Operating System :: OS Independent
Classifier: Programming Language :: Python
